acmen/__init__.py
acmen/__version__.py
acmen/acmen.py
acmen/enums.py
acmen/handlers.py
acmen-0.5.1.dist-info/METADATA
acmen-0.5.1.dist-info/WHEEL
acmen-0.5.1.dist-info/licenses/LICENSE
acmen-0.5.1.dist-info/RECORD
