Metadata-Version: 2.3
Name: acmen
Version: 0.5.1
Summary: An ACME(RFC8555) client implementation in Python.
Project-URL: Documentation, https://cbpj.github.io/AcmeN/
Project-URL: Source, https://github.com/CBPJ/AcmeN
Project-URL: Bug Tracker, https://github.com/CBPJ/AcmeN/issues
Author: Jiacheng Huo
License-File: LICENSE
Classifier: License :: OSI Approved :: MIT License
Classifier: Programming Language :: Python :: 3
Requires-Python: >=3.7
Requires-Dist: cryptography==42.*
Requires-Dist: dnspython==2.*
Requires-Dist: jwcrypto==1.*
Requires-Dist: requests==2.*
Requires-Dist: tld==0.13.*
